CONTRIBUTING.rst
MANIFEST.in
README.md
setup.py
crappyspider/__init__.py
crappyspider/items.py
crappyspider/middlewares.py
crappyspider/pipelines.py
crappyspider/settings.py
crappyspider.egg-info/PKG-INFO
crappyspider.egg-info/SOURCES.txt
crappyspider.egg-info/dependency_links.txt
crappyspider.egg-info/requires.txt
crappyspider.egg-info/top_level.txt
crappyspider/spiders/__init__.py
crappyspider/spiders/crappyspider.py
docs/Makefile
docs/make.bat
docs/source/command_line.rst
docs/source/conf.py
docs/source/config.rst
docs/source/devguide.rst
docs/source/index.rst
tests/basic.py