Metadata-Version: 1.1
Name: crappyspider
Version: 0.3
Summary: Test your site.
Home-page: http://crappyspider.readthedocs.org/en/latest/
Author: Peopledoc
Author-email: hobbestigrou@erakis.eu
License: UNKNOWN
Keywords: crawler,scrapy
Platform: UNKNOWN
Classifier: Programming Language :: Python
Classifier: Programming Language :: Python :: 3
Classifier: Development Status :: 4 - Beta
Classifier: Environment :: Other Environment
Classifier: Intended Audience :: Developers
Classifier: License :: OSI Approved :: BSD License
Classifier: Operating System :: OS Independent
Classifier: Topic :: Software Development :: Libraries :: Python Modules
